promptfit/__init__.py
promptfit/cli.py
promptfit/config.py
promptfit/config_multi_provider.py
promptfit/embedder.py
promptfit/multi_provider_optimizer.py
promptfit/optimizer.py
promptfit/paraphraser.py
promptfit/quality.py
promptfit/relevance.py
promptfit/summarizer.py
promptfit/token_budget.py
promptfit/utils.py
promptfit/providers/__init__.py
promptfit/providers/base.py
promptfit/providers/cohere_provider.py
promptfit/providers/gemini_provider.py
promptfit/providers/provider_manager.py
promptfit/tests/test_optimizer.py
promptfit/tests/test_paraphraser.py
promptfit/tests/test_relevance.py
promptfit/tests/test_token_budget.py
promptfit-0.5.0.dist-info/licenses/LICENSE
promptfit-0.5.0.dist-info/METADATA
promptfit-0.5.0.dist-info/WHEEL
promptfit-0.5.0.dist-info/top_level.txt
promptfit-0.5.0.dist-info/RECORD
