Metadata-Version: 2.4
Name: promptfit
Version: 0.5.0
Summary: Multi-provider LLM prompt optimization toolkit: compress prompts by 50-80% while preserving quality. Supports Cohere, Gemini with automatic failover. Perfect for RAG, API cost reduction, and production GenAI workflows.
Author-email: Vedant Laxman Chandore <vedantchandore5@email.com>
License: MIT
Project-URL: Homepage, https://github.com/VedantChandore/promptfit
Project-URL: Documentation, https://github.com/VedantChandore/promptfit#readme
Project-URL: Repository, https://github.com/VedantChandore/promptfit
Project-URL: Issues, https://github.com/VedantChandore/promptfit/issues
Keywords: llm,prompt,optimization,rag,ai,cohere,gemini,cost-reduction,genai
Classifier: Development Status :: 4 - Beta
Classifier: Intended Audience :: Developers
Classifier: License :: OSI Approved :: MIT License
Classifier: Programming Language :: Python :: 3
Classifier: Programming Language :: Python :: 3.10
Classifier: Programming Language :: Python :: 3.11
Classifier: Programming Language :: Python :: 3.12
Classifier: Topic :: Software Development :: Libraries :: Python Modules
Classifier: Topic :: Scientific/Engineering :: Artificial Intelligence
Classifier: Topic :: Text Processing :: Linguistic
Requires-Python: >=3.10
License-File: LICENSE
Requires-Dist: cohere>=4.37
Requires-Dist: google-generativeai>=0.3.0
Requires-Dist: scikit-learn>=1.0.0
Requires-Dist: numpy>=1.21.0
Requires-Dist: nltk>=3.8
Requires-Dist: python-dotenv>=0.19.0
Requires-Dist: rich>=13.0.0
Requires-Dist: typer>=0.9.0
Provides-Extra: dev
Requires-Dist: pytest>=7.0.0; extra == "dev"
Requires-Dist: pytest-asyncio>=0.21.0; extra == "dev"
Requires-Dist: black>=22.0.0; extra == "dev"
Requires-Dist: isort>=5.10.0; extra == "dev"
Requires-Dist: mypy>=0.991; extra == "dev"
Provides-Extra: production
Requires-Dist: structlog>=22.0.0; extra == "production"
Requires-Dist: prometheus-client>=0.15.0; extra == "production"
Requires-Dist: cachetools>=5.0.0; extra == "production"
Requires-Dist: tenacity>=8.0.0; extra == "production"
Requires-Dist: pydantic>=2.0.0; extra == "production"
Dynamic: license-file
